toydata/Graph.py
toydata/LinkedLists.py
toydata/Maps.py
toydata/PositionalList.py
toydata/PriorityQueue.py
toydata/Queue.py
toydata/SearchTree.py
toydata/Stack.py
toydata/Tree.py
toydata/__init__.py
toydata/utils.py
toydata-1.1.0.dist-info/METADATA
toydata-1.1.0.dist-info/LICENSE
toydata-1.1.0.dist-info/WHEEL
toydata-1.1.0.dist-info/RECORD
