Metadata-Version: 2.1
Name: toydata
Version: 1.1.0
Summary: Data Structures in Python
License: LGPL v3
Author: Xiangzhuang Shen
Author-email: datahonor@gmail.com
Requires-Python: >=3.9,<4.0
Classifier: License :: Other/Proprietary License
Classifier: Programming Language :: Python :: 3
Classifier: Programming Language :: Python :: 3.9
Classifier: Programming Language :: Python :: 3.10
Classifier: Programming Language :: Python :: 3.11
